vforge/cli.py
vforge/freeze.py
vforge/helpers.py
vforge/init.py
vforge/purge.py
vforge/sync.py
vforge-1.0.2.dist-info/METADATA
vforge-1.0.2.dist-info/WHEEL
vforge-1.0.2.dist-info/entry_points.txt
vforge-1.0.2.dist-info/top_level.txt
vforge-1.0.2.dist-info/RECORD
