Metadata-Version: 2.4
Name: vforge
Version: 1.0.2
Summary: vforge virtual environment manager
Author-email: Tommas Sessions <tsessions@wesleyan.edu>
License: GNU General Public License v3.0
Classifier: Programming Language :: Python :: 3
Classifier: License :: OSI Approved :: GNU General Public License v3 (GPLv3)
Classifier: Operating System :: OS Independent
Requires-Dist: pyyaml
Requires-Dist: stdlib-list
